lunanlp/__init__.py
lunanlp/collections.py
lunanlp/easy_logging.py
lunanlp/file.py
lunanlp/legacy_ml.py
lunanlp/pretty_printing.py
lunanlp/program_args.py
lunanlp/public.py
lunanlp/pytorch.py
lunanlp/ram.py
lunanlp/registry.py
lunanlp/sequence.py
lunanlp-1.0.dist-info/METADATA
lunanlp-1.0.dist-info/WHEEL
lunanlp-1.0.dist-info/top_level.txt
lunanlp-1.0.dist-info/RECORD
